internal/load_environment.py
internal/resource_manager.py
qgits/__init__.py
qgits/cli.py
qgits/qgit.py
qgits/qgit_benedict.py
qgits/qgit_cancel.py
qgits/qgit_commands.py
qgits/qgit_config.py
qgits/qgit_core.py
qgits/qgit_dict.py
qgits/qgit_doctor.py
qgits/qgit_errors.py
qgits/qgit_git.py
qgits/qgit_gui.py
qgits/qgit_last.py
qgits/qgit_logger.py
qgits/qgit_shove.py
qgits/qgit_snapshot.py
qgits/qgit_stats.py
qgits/qgit_undo.py
qgits/qgit_utils.py
qgits/qgit_visuals.py
qgits/setup_verification.py
qgits/qgit_author.py
qgits/qgit_author_data.py
qgit-1.1.4.dist-info/METADATA
qgit-1.1.4.dist-info/WHEEL
qgit-1.1.4.dist-info/entry_points.txt
qgit-1.1.4.dist-info/RECORD
