Metadata-Version: 2.4
Name: qgit
Version: 1.1.4
Summary: A powerful Git operations automation tool that provides enhanced Git workflow management, repository visualization, and security scanning capabilities.
Project-URL: Homepage, https://github.com/griffincancode/qgit
Project-URL: Repository, https://github.com/griffincancode/qgit.git
Project-URL: Issues, https://github.com/griffincancode/qgit/issues
Project-URL: Documentation, https://github.com/griffincancode/qgit#readme
Author-email: Griffin <griffin@griffin-code.com>
Maintainer-email: Griffin <griffin@griffin-code.com>
License-Expression: MIT
Keywords: automation,development,git,repository,security,tools,visualization,workflow
Classifier: Development Status :: 3 - Alpha
Classifier: Intended Audience :: Developers
Classifier: License :: OSI Approved :: MIT License
Classifier: Operating System :: OS Independent
Classifier: Programming Language :: Python :: 3
Classifier: Programming Language :: Python :: 3.8
Classifier: Programming Language :: Python :: 3.9
Classifier: Programming Language :: Python :: 3.10
Classifier: Programming Language :: Python :: 3.11
Classifier: Programming Language :: Python :: 3.12
Classifier: Topic :: Software Development :: Version Control :: Git
Requires-Python: >=3.8
Requires-Dist: gitpython>=2.20.0
Requires-Dist: numpy<2.0.0,>=1.26.0
Requires-Dist: pillow<11.0.0,>=10.1.0
Requires-Dist: psutil<6.0.0,>=5.9.6
Requires-Dist: pygame<3.0.0,>=2.5.2
Requires-Dist: pyopengl-accelerate<4.0.0,>=3.1.7
Requires-Dist: pyopengl<4.0.0,>=3.1.7
Requires-Dist: rich<14.0.0,>=13.7.0
Requires-Dist: tqdm<5.0.0,>=4.66.1
Provides-Extra: dev
Requires-Dist: black<24.0.0,>=23.11.0; extra == 'dev'
Requires-Dist: flake8<7.0.0,>=6.1.0; extra == 'dev'
Requires-Dist: isort<6.0.0,>=5.12.0; extra == 'dev'
Requires-Dist: mypy<2.0.0,>=1.7.0; extra == 'dev'
Requires-Dist: pytest-asyncio<1.0.0,>=0.23.0; extra == 'dev'
Requires-Dist: pytest-cov<5.0.0,>=4.1.0; extra == 'dev'
Requires-Dist: pytest<8.0.0,>=7.4.3; extra == 'dev'
